LICENSE
MANIFEST.in
README.md
setup.py
django_softdelete_ts.egg-info/PKG-INFO
django_softdelete_ts.egg-info/SOURCES.txt
django_softdelete_ts.egg-info/dependency_links.txt
django_softdelete_ts.egg-info/requires.txt
django_softdelete_ts.egg-info/top_level.txt
django_softdelete_ts.egg-info/zip-safe
softdelete/__init__.py
softdelete/forms.py
softdelete/models.py
softdelete/settings.py
softdelete/signals.py
softdelete/urls.py
softdelete/views.py
softdelete/admin/__init__.py
softdelete/admin/admin.py
softdelete/admin/forms.py
softdelete/migrations/0001_initial.py
softdelete/migrations/0002_auto_20170912_0537.py
softdelete/migrations/0003_auto_20211015_1406.py
softdelete/migrations/__init__.py
softdelete/south_migrations/0001_initial.py
softdelete/south_migrations/0002_auto__del_recordset__del_unique_recordset_changeset_content_type_objec.py
softdelete/south_migrations/0003_auto__chg_field_softdeleterecord_object_id__chg_field_changeset_object.py
softdelete/south_migrations/__init__.py
softdelete/templates/base.html
softdelete/templates/admin/softdelete/change_form.html
softdelete/templates/admin/softdelete/changeset/change_form.html
softdelete/templates/admin/softdelete/softdeleterecord/change_form.html
softdelete/templates/softdelete/base.html
softdelete/templates/softdelete/changeset_detail.html
softdelete/templates/softdelete/changeset_form.html
softdelete/templates/softdelete/changeset_list.html
softdelete/templates/softdelete/stubs/changeset_detail.html
softdelete/test_softdelete_app/__init__.py
softdelete/test_softdelete_app/exceptions.py
softdelete/test_softdelete_app/models.py
softdelete/tests/__init__.py
softdelete/tests/constanats.py
softdelete/tests/test_sd.py
softdelete/tests/test_views.py