Metadata-Version: 2.1
Name: django-softdelete-ts
Version: 0.9.5
Summary: Soft delete support for Django ORM, with undelete.
Home-page: https://github.com/jackeygao/django-softdelete
Author: Steve Coursen
Author-email: smcoursen@gmail.com
Maintainer: Steve Coursen
Maintainer-email: smcoursen@gmail.com
License: BSD
Classifier: Framework :: Django
Classifier: License :: OSI Approved :: BSD License
Classifier: Environment :: Web Environment
License-File: LICENSE
